esd_services_api_client/__init__.py
esd_services_api_client/beast/__init__.py
esd_services_api_client/beast/v3/__init__.py
esd_services_api_client/beast/v3/_connector.py
esd_services_api_client/beast/v3/_models.py
esd_services_api_client/boxer/README.md
esd_services_api_client/boxer/__init__.py
esd_services_api_client/boxer/_auth.py
esd_services_api_client/boxer/_base.py
esd_services_api_client/boxer/_connector.py
esd_services_api_client/boxer/_models.py
esd_services_api_client/common/__init__.py
esd_services_api_client/crystal/__init__.py
esd_services_api_client/crystal/_api_versions.py
esd_services_api_client/crystal/_connector.py
esd_services_api_client/crystal/_models.py
esd_services_api_client/nexus/README.md
esd_services_api_client/nexus/__init__.py
esd_services_api_client/nexus/abstractions/__init__.py
esd_services_api_client/nexus/abstractions/algrorithm_cache.py
esd_services_api_client/nexus/abstractions/input_object.py
esd_services_api_client/nexus/abstractions/logger_factory.py
esd_services_api_client/nexus/abstractions/metrics_provider_factory.py
esd_services_api_client/nexus/abstractions/nexus_object.py
esd_services_api_client/nexus/abstractions/socket_provider.py
esd_services_api_client/nexus/algorithms/__init__.py
esd_services_api_client/nexus/algorithms/_baseline_algorithm.py
esd_services_api_client/nexus/algorithms/_remote_algorithm.py
esd_services_api_client/nexus/algorithms/distributed.py
esd_services_api_client/nexus/algorithms/forked_algorithm.py
esd_services_api_client/nexus/algorithms/minimalistic.py
esd_services_api_client/nexus/algorithms/recursive.py
esd_services_api_client/nexus/configurations/__init__.py
esd_services_api_client/nexus/configurations/algorithm_configuration.py
esd_services_api_client/nexus/core/__init__.py
esd_services_api_client/nexus/core/app_core.py
esd_services_api_client/nexus/core/app_dependencies.py
esd_services_api_client/nexus/core/serializers.py
esd_services_api_client/nexus/exceptions/__init__.py
esd_services_api_client-2.7.3.dist-info/LICENSE
esd_services_api_client-2.7.3.dist-info/METADATA
esd_services_api_client-2.7.3.dist-info/WHEEL
esd_services_api_client-2.7.3.dist-info/RECORD
