Metadata-Version: 2.3
Name: esd-services-api-client
Version: 2.7.3
Summary: Python clients for ESD services
License: Apache-2.0
Author: ECCO Sneaks & Data
Author-email: esdsupport@ecco.com
Maintainer: GZU
Maintainer-email: gzu@ecco.com
Requires-Python: >=3.11,<3.12
Classifier: License :: OSI Approved :: Apache Software License
Classifier: Programming Language :: Python :: 3
Classifier: Programming Language :: Python :: 3.11
Provides-Extra: azure
Provides-Extra: nexus
Requires-Dist: adapta[datadog,storage] (>=3.5.2,<3.6.0)
Requires-Dist: azure-identity (>=1.7,<1.8) ; extra == "azure"
Requires-Dist: dataclasses-json (>=0.6.0,<0.7.0)
Requires-Dist: httpx (>=0.27.0,<0.28.0) ; extra == "nexus"
Requires-Dist: injector (>=0.22.0,<0.23.0) ; extra == "nexus"
Requires-Dist: pycryptodome (>=3.15,<3.16)
Requires-Dist: pyjwt (>=2.4.0,<2.5.0)
Project-URL: Repository, https://github.com/SneaksAndData/esd-services-api-client
